eddies_tools/__init__.py
eddies_tools/basic_funcs.js
eddies_tools/chart_bar.js
eddies_tools/chart_bar_categorical.js
eddies_tools/chart_line.js
eddies_tools/chart_line_time.js
eddies_tools/chart_scatter.js
eddies_tools/chart_scatter_time.js
eddies_tools/css.css
eddies_tools/date_time.py
eddies_tools/db_info.py
eddies_tools/db_objects.py
eddies_tools/dividers.css
eddies_tools/dividers.py
eddies_tools/dividers_funcs.js
eddies_tools/home.py
eddies_tools/html_builder.py
eddies_tools/lazy_table.css
eddies_tools/lazy_table.py
eddies_tools/lazy_table_funcs.js
eddies_tools/lazy_tree.css
eddies_tools/lazy_tree.py
eddies_tools/lazy_tree_funcs.js
eddies_tools/mysql_query_builder.py
eddies_tools/read_creds.py
eddies_tools/rich_text_editor.css
eddies_tools/rich_text_editor.py
eddies_tools/rich_text_editor_funcs.js
eddies_tools/router.py
eddies_tools/tabs.css
eddies_tools/tabs.py
eddies_tools/tabs_funcs.js
eddies_tools/test_client.py
eddies_tools-0.0.31.dist-info/licenses/LICENSE
eddies_tools-0.0.31.dist-info/METADATA
eddies_tools-0.0.31.dist-info/WHEEL
eddies_tools-0.0.31.dist-info/top_level.txt
eddies_tools-0.0.31.dist-info/RECORD
